serpengine/ dataforseo_search.py
serpengine/__init__.py
serpengine/base_channel.py
serpengine/channel_manager.py
serpengine/google_search_api.py
serpengine/myllmservice.py
serpengine/old_serpengine.py
serpengine/schemas.py
serpengine/serpapi_searcher.py
serpengine/serpengine.py
serpengine/test.py
serpengine/utils.py
serpengine-0.1.4.2.dist-info/METADATA
serpengine-0.1.4.2.dist-info/WHEEL
serpengine-0.1.4.2.dist-info/top_level.txt
serpengine-0.1.4.2.dist-info/RECORD
